inquant/AssetInfo.py
inquant/BarData.py
inquant/Contract.py
inquant/Order.py
inquant/Position.py
inquant/StrategyTemplate.py
inquant/TickData.py
inquant/__init__.py
inquant/example/MyStrategy.py
inquant/example/__init__.py
inquant/framework/IBaseDataApi.py
inquant/framework/IMarketApi.py
inquant/framework/IStrategyService.py
inquant/framework/ITradeApi.py
inquant/framework/StrategyService.py
inquant/framework/__init__.py
inquant/future/FutDataApi.py
inquant/future/FutMarketApi.py
inquant/future/FutPaperTradeApi.py
inquant/future/__init__.py
inquant/util/DES3Cryptogram.py
inquant/util/HttpHelper.py
inquant/util/LogRecord.py
inquant/util/LongTcpClient.py
inquant/util/MemCache.py
inquant/util/__init__.py
inquant-1.3.1.dist-info/LICENSE
inquant-1.3.1.dist-info/METADATA
inquant-1.3.1.dist-info/WHEEL
inquant-1.3.1.dist-info/top_level.txt
inquant-1.3.1.dist-info/RECORD
